CYuyanBianchengRuanjianWanquanGonglveCYuyanBianchengWangFix1/README.md
CYuyanBianchengRuanjianWanquanGonglveCYuyanBianchengWangFix1/__init__.py
CYuyanBianchengRuanjianWanquanGonglveCYuyanBianchengWangFix1/__main__.py
CYuyanBianchengRuanjianWanquanGonglveCYuyanBianchengWangFix1/file.epub
CYuyanBianchengRuanjianWanquanGonglveCYuyanBianchengWangFix1/index.html
CYuyanBianchengRuanjianWanquanGonglveCYuyanBianchengWangFix1/css/__init__.py
CYuyanBianchengRuanjianWanquanGonglveCYuyanBianchengWangFix1/css/annotations.css
CYuyanBianchengRuanjianWanquanGonglveCYuyanBianchengWangFix1/css/main.css
CYuyanBianchengRuanjianWanquanGonglveCYuyanBianchengWangFix1/css/normalize.css
CYuyanBianchengRuanjianWanquanGonglveCYuyanBianchengWangFix1/css/popup.css
CYuyanBianchengRuanjianWanquanGonglveCYuyanBianchengWangFix1/font/__init__.py
CYuyanBianchengRuanjianWanquanGonglveCYuyanBianchengWangFix1/font/fontello.eot
CYuyanBianchengRuanjianWanquanGonglveCYuyanBianchengWangFix1/font/fontello.svg
CYuyanBianchengRuanjianWanquanGonglveCYuyanBianchengWangFix1/font/fontello.ttf
CYuyanBianchengRuanjianWanquanGonglveCYuyanBianchengWangFix1/font/fontello.woff
CYuyanBianchengRuanjianWanquanGonglveCYuyanBianchengWangFix1/img/__init__.py
CYuyanBianchengRuanjianWanquanGonglveCYuyanBianchengWangFix1/img/annotator-glyph-sprite.png
CYuyanBianchengRuanjianWanquanGonglveCYuyanBianchengWangFix1/img/annotator-icon-sprite.png
CYuyanBianchengRuanjianWanquanGonglveCYuyanBianchengWangFix1/img/apple-touch-icon.png
CYuyanBianchengRuanjianWanquanGonglveCYuyanBianchengWangFix1/img/cancelfullscreen.png
CYuyanBianchengRuanjianWanquanGonglveCYuyanBianchengWangFix1/img/close.png
CYuyanBianchengRuanjianWanquanGonglveCYuyanBianchengWangFix1/img/fullscreen.png
CYuyanBianchengRuanjianWanquanGonglveCYuyanBianchengWangFix1/img/loader.gif
CYuyanBianchengRuanjianWanquanGonglveCYuyanBianchengWangFix1/img/menu-icon.png
CYuyanBianchengRuanjianWanquanGonglveCYuyanBianchengWangFix1/img/save.png
c_yuyan_biancheng_ruanjian_wanquan_gonglve_c_yuyan_biancheng_wang_fix1-2025.3.24.0.dist-info/METADATA
c_yuyan_biancheng_ruanjian_wanquan_gonglve_c_yuyan_biancheng_wang_fix1-2025.3.24.0.dist-info/WHEEL
c_yuyan_biancheng_ruanjian_wanquan_gonglve_c_yuyan_biancheng_wang_fix1-2025.3.24.0.dist-info/entry_points.txt
c_yuyan_biancheng_ruanjian_wanquan_gonglve_c_yuyan_biancheng_wang_fix1-2025.3.24.0.dist-info/top_level.txt
c_yuyan_biancheng_ruanjian_wanquan_gonglve_c_yuyan_biancheng_wang_fix1-2025.3.24.0.dist-info/RECORD
